AUTHORS.rst
CONTRIBUTING.rst
HISTORY.rst
LICENSE
MANIFEST.in
README.rst
requirements.txt
requirements_dev.txt
setup.cfg
setup.py
docs/Makefile
docs/authors.rst
docs/conf.py
docs/contributing.rst
docs/history.rst
docs/index.rst
docs/installation.rst
docs/make.bat
docs/readme.rst
docs/usage.rst
es_peek.egg-info/PKG-INFO
es_peek.egg-info/SOURCES.txt
es_peek.egg-info/dependency_links.txt
es_peek.egg-info/entry_points.txt
es_peek.egg-info/not-zip-safe
es_peek.egg-info/requires.txt
es_peek.egg-info/top_level.txt
peek/__init__.py
peek/ast.py
peek/capture.py
peek/cli.py
peek/common.py
peek/completer.py
peek/completions.py
peek/config.py
peek/connection.py
peek/display.py
peek/errors.py
peek/history.py
peek/key_bindings.py
peek/krb.py
peek/lexers.py
peek/natives.py
peek/oidc.py
peek/parser.py
peek/peekapp.py
peek/peekrc
peek/saml.py
peek/visitors.py
peek/vm.py
peek/certs/cert.pem
peek/certs/key.pem
peek/es_api_spec/__init__.py
peek/es_api_spec/api_completer.py
peek/es_api_spec/kspec.py
peek/es_api_spec/kspec_js.py
peek/es_api_spec/kspec_json.py
peek/es_api_spec/schema.py
tests/__init__.py
tests/payload.json
tests/test_completer.py
tests/test_completions.py
tests/test_connection.py
tests/test_display.py
tests/test_key_bindings.py
tests/test_lexers.py
tests/test_natives.py
tests/test_parser.py
tests/test_peekapp.py
tests/test_schema_completer.py
tests/test_visitors.py
tests/test_vm.py
tests/es_api_spec/__init__.py
tests/es_api_spec/test_spec.py
tests/es_api_spec/test_spec_js.py