Metadata-Version: 2.1
Name: es-peek
Version: 0.3.1
Summary: Peek into elasticsearch clusters
Home-page: https://github.com/ywangd/peek
Author: Yang Wang
Author-email: ywangd@gmail.com
License: MIT license
Keywords: peek,elasticsearch,cli
Classifier: Development Status :: 5 - Production/Stable
Classifier: Intended Audience :: Developers
Classifier: License :: OSI Approved :: MIT License
Classifier: Natural Language :: English
Classifier: Programming Language :: Python :: 3
Classifier: Programming Language :: Python :: 3.8
Classifier: Programming Language :: Python :: 3.9
Classifier: Programming Language :: Python :: 3.10
Requires-Python: >=3.8
Provides-Extra: full
License-File: LICENSE
License-File: AUTHORS.rst
